ggmlipidclassifier-0.1.3.dist-info/licenses/LICENSE
glc/__init__.py
glc/data_loading.py
glc/glc_model.py
glc/ground_truth_validation.py
glc/ion_processor.py
glc/load_ggm.py
glc/logp_filtering.py
glc/mz_peak_picking.py
glc/quality_scores.py
glc/umap_model_and_plots.py
glc/data/__init__.py
glc/data/esi_mass_differences.parquet
glc/data/example_feature_table_addneuromed_lpos.parquet
glc/data/example_ggm_addneuromed_lpos.parquet
glc/data/example_ground_truth_addneuromed_lpos.parquet
glc/data/lipid_maps_database.parquet
glc/data/__pycache__/__init__.cpython-311.pyc
ggmlipidclassifier-0.1.3.dist-info/METADATA
ggmlipidclassifier-0.1.3.dist-info/WHEEL
ggmlipidclassifier-0.1.3.dist-info/top_level.txt
ggmlipidclassifier-0.1.3.dist-info/RECORD
