Metadata-Version: 2.4
Name: ggmlipidclassifier
Version: 0.1.3
Summary: GGM Lipid Classifier for lipid class prediction of features from untargeted lipidomic LC-MS
Author-email: tom rix <tom.rix21@imperial.ac.uk>
Requires-Python: >=3.11
License-File: LICENSE
Requires-Dist: colorcet>=3.1.0
Requires-Dist: matplotlib>=3.10.7
Requires-Dist: molmass>=2025.11.11
Requires-Dist: networkx>=3.6
Requires-Dist: numpy>=2.3.5
Requires-Dist: pandas>=2.3.3
Requires-Dist: pyarrow>=22.0.0
Requires-Dist: rpy2<=3.6
Requires-Dist: scikit-learn>=1.7.2
Requires-Dist: scipy>=1.16.3
Requires-Dist: seaborn>=0.13.2
Requires-Dist: tqdm>=4.67.1
Requires-Dist: umap-learn>=0.5.9.post2
Dynamic: license-file
